{
    "glucose_bride_a": {
        "name": {
            "text": "Глюкоза Невеста"
        },
        "original": {
            "text": "Я буду вместо, вместо, вместо неё \n Твоя невеста честно, честная Ё. \n Я буду вместо, вместо, вместо неё твоя! Я!"
        },
        "puzzle": {
            "text": "Я клянусь, что никогда не обману тебя, если ты заменишь свою будующую жену на меня!"
        },
        "close": ["^невест", "^твоя", "^честн"],
        "win": ["глюкоза", "^невест.", "^твоя", "вместо", "^честн"]
    },
    "zhuki_battery_a": {
        "name": {
            "text": "Жуки Батарейка"
        },
        "original": {
            "text": "Холодный ветер с дождем усилился стократно \n Все говорит об одном, что нет пути обратно."
        },
        "puzzle": {
            "text": "Леденящий порыв воздуха и атмосферные осадки усилились в 100 раз. Все это указывает на единственный факт, что дороги назад нет."
        },
        "close": ["батарейк", "^дожд", "^вет"],
        "win": ["жуки", "^батарейка", "холодный", "ветер$", "стократно", "обратно"]
    },
    "demo_sun_a": {
        "name": {
            "text": "Демо Солнышко"
        },
        "original": {
            "text": "Солнышко в руках и венок из звезд в небесах, \n И с других планет все видят нас, мне так хорошо с тобой мечтать об этом."
        },
        "puzzle": {
            "text": "Небесное светило в лодонях, венец из небесных тел в атмосфере. Инопланетяне наблюдают за нами, как прекрасно вместе об этом думать."
        },
        "close": ["^cолн", "^неб", "^рук", "^планет"],
        "win": ["^д.мо$", "^cолн", "^рук", "^планет", "мечтать", "хорошо"]
    }
}
